eminusmap/__init__.py
eminusmap/eminusmap.py
eminusmap-0.0.3.dist-info/LICENSE.txt
eminusmap-0.0.3.dist-info/METADATA
eminusmap-0.0.3.dist-info/WHEEL
eminusmap-0.0.3.dist-info/top_level.txt
eminusmap-0.0.3.dist-info/RECORD
